LogicGate.py
lgEncrypt.py
logicgate-0.3.0.dist-info/WHEEL
logicgate-0.3.0.dist-info/METADATA
logicgate-0.3.0.dist-info/LICENSE
logicgate-0.3.0.dist-info/RECORD
