Metadata-Version: 2.1
Name: logicgate
Version: 0.3.0
Summary: an esolang designed for manual encryption with logic gates
Home-page: https://replit.com/@s3D27ZHOU/LogicGate
License: MIT
Keywords: logic,gate,encrypt,encryption
Author: Taokyle
Author-email: taokyle415@gmail.com
Requires-Python: >=3.10,<4.0
Classifier: License :: OSI Approved :: MIT License
Classifier: Programming Language :: Python :: 3
Classifier: Programming Language :: Python :: 3.10
Classifier: Programming Language :: Python :: 3.11
Project-URL: Repository, https://replit.com/@s3D27ZHOU/LogicGate
Project-URL: github, https://github.com/TaokyleYT/LogicGate
Project-URL: outdated esolang wiki, https://esolangs.org/wiki/LogicGate
Project-URL: up-to-date source code(replit), https://replit.com/@s3D27ZHOU/LogicGate
